{"cameraMode":{"drawMode":0,"name":"Shaded","section":"Shading Mode"},"sceneLighting":true,"audioPlay":false,"sceneViewState":{"m_AlwaysRefresh":false,"showFog":true,"showSkybox":true,"showFlares":true,"showImageEffects":true,"showParticleSystems":true,"showVisualEffectGraphs":true,"m_FxEnabled":true},"in2DMode":false,"pivot":{"x":-7.366196632385254,"y":-0.28816890716552737,"z":3.838437557220459},"rotation":{"x":-0.18071359395980836,"y":0.6963918805122376,"z":-0.1882409304380417,"w":-0.6685449481010437},"size":31.63844108581543,"orthographic":false}